Workbook
Name aporte: Planilha1!$F$16:$F$16
Name patrimonio: Planilha1!$F$19:$F$19
Name qtd_anos: Planilha1!$F$17:$F$17
Name rendimento: Planilha1!$B$17:$B$17
Name salario: Planilha1!$B$16:$B$16
Name sugestao_investimento: Planilha1!$B$18:$B$18
Name taxa_mensal: Planilha1!$F$18:$F$18

Sheet Planilha1
A15: INSERSOÇÕES | C15: 2 | D15: INVESTIMENTO MENSAL
A16: Salário | B16: 21000 | C16: 5 | D16: Quanto investir por mês ? | F16: 6300
A17: Rendimento Carteira | B17: 0.01 | C17: 10 | D17: Por Quantos Anos ? | F17: 5
A18: Sugestão de Investimento (30%) | B18: =B16*30% -> 6300 | C18: 20 | D18: Taxa de Rendimento mensal ? | F18: 0.01079
C19: 30 | D19: Patrimônio acumulado ? | F19: =FV(taxa_mensal,qtd_anos*12,aporte*-1) -> 527794.56
D20: Dividendos Mensais ? | F20: {=patrimonio*rendimento} -> 5277.9456
A23: Cenários | B23: Dividendo
A24: Quanto em 2 Anos ? | B24: {=FV($B$17,C15*12,aporte*-1)} -> 169932.83 | C24: {=B24*rendimento} -> 1699.3283
A25: Quanto em 5 Anos ? | B25: {=FV($B$17,C16*12,aporte*-1)} -> 514518.92 | C25: {=B25*rendimento} -> 5145.1892
A26: Quanto em 10 Anos ? | B26: {=FV($B$17,C17*12,aporte*-1)} -> 1449243.7 | C26: {=B26*rendimento} -> 14492.437
A27: Quanto em 20 Anos ? | B27: {=FV($B$17,C18*12,aporte*-1)} -> 6232308.8 | C27: {=B27*rendimento} -> 62323.088
A28: Quanto em 30 Anos ? | B28: {=FV($B$17,C19*12,aporte*-1)} -> 22018274 | C28: {=B28*rendimento} -> 220182.74
A31: PERFIL | B31: Agressivo
A32: VALOR A SER INVESTIDO POR MÊS | B32: =aporte -> 6300
A34: TIPO DE FII | B34: Percentual Sugerido | C34: Valores
A35: PAPEL | B35: =VLOOKUP($B$31&"-"&A35,Planilha2!$A:$D,4,FALSE) -> 0.25 | C35: =B35*$B$32 -> 1575
A36: TIJOLO | B36: =VLOOKUP($B$31&"-"&A36,Planilha2!$A:$D,4,FALSE) -> 0.35 | C36: =B36*$B$32 -> 2205
A37: HÍBRIDOS | B37: =VLOOKUP($B$31&"-"&A37,Planilha2!$A:$D,4,FALSE) -> 0.1 | C37: =B37*$B$32 -> 630
A38: FOFs | B38: =VLOOKUP($B$31&"-"&A38,Planilha2!$A:$D,4,FALSE) -> 0.05 | C38: =B38*$B$32 -> 315
A39: DESENVOLVIMENTO | B39: =VLOOKUP($B$31&"-"&A39,Planilha2!$A:$D,4,FALSE) -> 0.15 | C39: =B39*$B$32 -> 945
A40: HOTELARIAS | B40: =VLOOKUP($B$31&"-"&A40,Planilha2!$A:$D,4,FALSE) -> 0.1 | C40: =B40*$B$32 -> 630
A41: TOTAL | C41: =SUM(C35:C40) -> 6300

Sheet Planilha2
A1: CHAVE | B1: PERFIL | C1: TIPO DE FII | D1: %
A2: =B2&"-"&C2 -> Conservador-PAPEL | B2: Conservador | C2: PAPEL | D2: 0.35
A3: =B3&"-"&C3 -> Conservador-TIJOLO | B3: Conservador | C3: TIJOLO | D3: 0.5
A4: =B4&"-"&C4 -> Conservador-HÍBRIDOS | B4: Conservador | C4: HÍBRIDOS | D4: 0.1
A5: =B5&"-"&C5 -> Conservador-FOFs | B5: Conservador | C5: FOFs | D5: 0.05
A6: =B6&"-"&C6 -> Conservador-DESENVOLVIMENTO | B6: Conservador | C6: DESENVOLVIMENTO | D6: 0
A7: =B7&"-"&C7 -> Conservador-HOTELARIAS | B7: Conservador | C7: HOTELARIAS | D7: 0
A8: =B8&"-"&C8 -> Moderado-PAPEL | B8: Moderado | C8: PAPEL | D8: 0.3
A9: =B9&"-"&C9 -> Moderado-TIJOLO | B9: Moderado | C9: TIJOLO | D9: 0.45
A10: =B10&"-"&C10 -> Moderado-HÍBRIDOS | B10: Moderado | C10: HÍBRIDOS | D10: 0.1
A11: =B11&"-"&C11 -> Moderado-FOFs | B11: Moderado | C11: FOFs | D11: 0.05
A12: =B12&"-"&C12 -> Moderado-DESENVOLVIMENTO | B12: Moderado | C12: DESENVOLVIMENTO | D12: 0.05
A13: =B13&"-"&C13 -> Moderado-HOTELARIAS | B13: Moderado | C13: HOTELARIAS | D13: 0.05
... A19: =B19&"-"&C19 -> Agressivo-HOTELARIAS | B19: Agressivo | C19: HOTELARIAS | D19: 0.1
E27: =PROCV($C$32&"-"&B36,Planilha2$A:$D,4,FALSO)
